Workbook

Sheet Read Me
A1: Sciuro — UAT Test Tracker
A2: Covers every module and functionality planned across the engineering, UI/UX, and automation discussions.
A4: How to use this workbook
A5: 1. Work through the 'UAT Test Cases' sheet, module by module — the Phase column tells you roughly which build phase (from the v4 engineering plan) needs to be done before that test is runnable.
A6: 2. Set Status for each row using the dropdown: Not Tested, Pass, Fail, Blocked, N/A.
A7: 3. Record what actually happened in 'Actual Result / Notes' whenever it differs from Expected — this is especially useful for Fail and Blocked rows.
A8: 4. Fill in Tested By and Date Tested as you go.
A9: 5. Check the 'Summary Dashboard' sheet for a live pass/fail rollup by module — it recalculates automatically as you update Status.
A11: Column reference
A12: Test ID — short code, prefixed by module (e.g. PAR-03 = Parsing test #3)
A13: Priority — Critical: must work correctly before anything else is trustworthy. High: core module correctness. Medium: UX polish and secondary paths. Low: nice-to-have / deferred scope.
A14: Phase — approximate mapping back to the v4 engineering plan's milestones/phases (A0-A6, B1-B7, C1-C3, D1-D3) or the automation plan. A guide for sequencing, not a rigid contract.
... A19: Desktop Companion tests are Low priority since that scope was explicitly deferred in the engineering plan — include them for completeness, not urgency.

Sheet Summary Dashboard
A1: Sciuro UAT — Summary Dashboard
A2: Recalculates automatically from the UAT Test Cases sheet as Status is updated.
A4: Overall
A5: Total Tests | B5: Passed | C5: Failed | D5: Blocked | E5: Not Tested | F5: N/A | G5: % Complete | H5: % Pass Rate (of tested)
A6: =COUNTA('UAT Test Cases'!$J$2:$J$117) -> 116 | B6: =COUNTIF('UAT Test Cases'!$J$2:$J$117,"Pass") -> 0 | C6: =COUNTIF('UAT Test Cases'!$J$2:$J$117,"Fail") -> 0 | D6: =COUNTIF('UAT Test Cases'!$J$2:$J$117,"Blocked") -> 0 | E6: =COUNTIF('UAT Test Cases'!$J$2:$J$117,"Not Tested") -> 116 | F6: =COUNTIF('UAT Test Cases'!$J$2:$J$117,"N/A") -> 0 | G6: =IFERROR((B6+C6+D6+F6)/A6,0) -> 0 | H6: =IFERROR(B6/(B6+C6),0) -> 0
A9: By Module
A10: Module | B10: Total | C10: Passed | D10: Failed | E10: Blocked | F10: Not Tested | G10: % Complete
A11: Onboarding | B11: =COUNTIF('UAT Test Cases'!$B$2:$B$117,$A11) -> 4 | C11: =COUNTIFS('UAT Test Cases'!$B$2:$B$117,$A11,'UAT Test Cases'!$J$2:$J$117,"Pass") -> 0 | D11: =COUNTIFS('UAT Test Cases'!$B$2:$B$117,$A11,'UAT Test Cases'!$J$2:$J$117,"Fail") -> 0 | E11: =COUNTIFS('UAT Test Cases'!$B$2:$B$117,$A11,'UAT Test Cases'!$J$2:$J$117,"Blocked") -> 0 | F11: =COUNTIFS('UAT Test Cases'!$B$2:$B$117,$A11,'UAT Test Cases'!$J$2:$J$117,"Not Tested") -> 4 | G11: =IFERROR((C11+D11+E11)/B11,0) -> 0
A12: Notification Capture | B12: =COUNTIF('UAT Test Cases'!$B$2:$B$117,$A12) -> 6 | C12: =COUNTIFS('UAT Test Cases'!$B$2:$B$117,$A12,'UAT Test Cases'!$J$2:$J$117,"Pass") -> 0 | D12: =COUNTIFS('UAT Test Cases'!$B$2:$B$117,$A12,'UAT Test Cases'!$J$2:$J$117,"Fail") -> 0 | E12: =COUNTIFS('UAT Test Cases'!$B$2:$B$117,$A12,'UAT Test Cases'!$J$2:$J$117,"Blocked") -> 0 | F12: =COUNTIFS('UAT Test Cases'!$B$2:$B$117,$A12,'UAT Test Cases'!$J$2:$J$117,"Not Tested") -> 6 | G12: =IFERROR((C12+D12+E12)/B12,0) -> 0
A13: Parsing | B13: =COUNTIF('UAT Test Cases'!$B$2:$B$117,$A13) -> 8 | C13: =COUNTIFS('UAT Test Cases'!$B$2:$B$117,$A13,'UAT Test Cases'!$J$2:$J$117,"Pass") -> 0 | D13: =COUNTIFS('UAT Test Cases'!$B$2:$B$117,$A13,'UAT Test Cases'!$J$2:$J$117,"Fail") -> 0 | E13: =COUNTIFS('UAT Test Cases'!$B$2:$B$117,$A13,'UAT Test Cases'!$J$2:$J$117,"Blocked") -> 0 | F13: =COUNTIFS('UAT Test Cases'!$B$2:$B$117,$A13,'UAT Test Cases'!$J$2:$J$117,"Not Tested") -> 8 | G13: =IFERROR((C13+D13+E13)/B13,0) -> 0
A14: Triage & Categorization | B14: =COUNTIF('UAT Test Cases'!$B$2:$B$117,$A14) -> 6 | C14: =COUNTIFS('UAT Test Cases'!$B$2:$B$117,$A14,'UAT Test Cases'!$J$2:$J$117,"Pass") -> 0 | D14: =COUNTIFS('UAT Test Cases'!$B$2:$B$117,$A14,'UAT Test Cases'!$J$2:$J$117,"Fail") -> 0 | E14: =COUNTIFS('UAT Test Cases'!$B$2:$B$117,$A14,'UAT Test Cases'!$J$2:$J$117,"Blocked") -> 0 | F14: =COUNTIFS('UAT Test Cases'!$B$2:$B$117,$A14,'UAT Test Cases'!$J$2:$J$117,"Not Tested") -> 6 | G14: =IFERROR((C14+D14+E14)/B14,0) -> 0
A15: Transfer Detection | B15: =COUNTIF('UAT Test Cases'!$B$2:$B$117,$A15) -> 6 | C15: =COUNTIFS('UAT Test Cases'!$B$2:$B$117,$A15,'UAT Test Cases'!$J$2:$J$117,"Pass") -> 0 | D15: =COUNTIFS('UAT Test Cases'!$B$2:$B$117,$A15,'UAT Test Cases'!$J$2:$J$117,"Fail") -> 0 | E15: =COUNTIFS('UAT Test Cases'!$B$2:$B$117,$A15,'UAT Test Cases'!$J$2:$J$117,"Blocked") -> 0 | F15: =COUNTIFS('UAT Test Cases'!$B$2:$B$117,$A15,'UAT Test Cases'!$J$2:$J$117,"Not Tested") -> 6 | G15: =IFERROR((C15+D15+E15)/B15,0) -> 0
A16: Physical Cash Wallet | B16: =COUNTIF('UAT Test Cases'!$B$2:$B$117,$A16) -> 5 | C16: =COUNTIFS('UAT Test Cases'!$B$2:$B$117,$A16,'UAT Test Cases'!$J$2:$J$117,"Pass") -> 0 | D16: =COUNTIFS('UAT Test Cases'!$B$2:$B$117,$A16,'UAT Test Cases'!$J$2:$J$117,"Fail") -> 0 | E16: =COUNTIFS('UAT Test Cases'!$B$2:$B$117,$A16,'UAT Test Cases'!$J$2:$J$117,"Blocked") -> 0 | F16: =COUNTIFS('UAT Test Cases'!$B$2:$B$117,$A16,'UAT Test Cases'!$J$2:$J$117,"Not Tested") -> 5 | G16: =IFERROR((C16+D16+E16)/B16,0) -> 0
A17: E-Wallet Accounts | B17: =COUNTIF('UAT Test Cases'!$B$2:$B$117,$A17) -> 5 | C17: =COUNTIFS('UAT Test Cases'!$B$2:$B$117,$A17,'UAT Test Cases'!$J$2:$J$117,"Pass") -> 0 | D17: =COUNTIFS('UAT Test Cases'!$B$2:$B$117,$A17,'UAT Test Cases'!$J$2:$J$117,"Fail") -> 0 | E17: =COUNTIFS('UAT Test Cases'!$B$2:$B$117,$A17,'UAT Test Cases'!$J$2:$J$117,"Blocked") -> 0 | F17: =COUNTIFS('UAT Test Cases'!$B$2:$B$117,$A17,'UAT Test Cases'!$J$2:$J$117,"Not Tested") -> 5 | G17: =IFERROR((C17+D17+E17)/B17,0) -> 0
A18: Recurring Obligations | B18: =COUNTIF('UAT Test Cases'!$B$2:$B$117,$A18) -> 6 | C18: =COUNTIFS('UAT Test Cases'!$B$2:$B$117,$A18,'UAT Test Cases'!$J$2:$J$117,"Pass") -> 0 | D18: =COUNTIFS('UAT Test Cases'!$B$2:$B$117,$A18,'UAT Test Cases'!$J$2:$J$117,"Fail") -> 0 | E18: =COUNTIFS('UAT Test Cases'!$B$2:$B$117,$A18,'UAT Test Cases'!$J$2:$J$117,"Blocked") -> 0 | F18: =COUNTIFS('UAT Test Cases'!$B$2:$B$117,$A18,'UAT Test Cases'!$J$2:$J$117,"Not Tested") -> 6 | G18: =IFERROR((C18+D18+E18)/B18,0) -> 0
A19: Debt Ledger | B19: =COUNTIF('UAT Test Cases'!$B$2:$B$117,$A19) -> 7 | C19: =COUNTIFS('UAT Test Cases'!$B$2:$B$117,$A19,'UAT Test Cases'!$J$2:$J$117,"Pass") -> 0 | D19: =COUNTIFS('UAT Test Cases'!$B$2:$B$117,$A19,'UAT Test Cases'!$J$2:$J$117,"Fail") -> 0 | E19: =COUNTIFS('UAT Test Cases'!$B$2:$B$117,$A19,'UAT Test Cases'!$J$2:$J$117,"Blocked") -> 0 | F19: =COUNTIFS('UAT Test Cases'!$B$2:$B$117,$A19,'UAT Test Cases'!$J$2:$J$117,"Not Tested") -> 7 | G19: =IFERROR((C19+D19+E19)/B19,0) -> 0
A20: Balance & Reconciliation | B20: =COUNTIF('UAT Test Cases'!$B$2:$B$117,$A20) -> 4 | C20: =COUNTIFS('UAT Test Cases'!$B$2:$B$117,$A20,'UAT Test Cases'!$J$2:$J$117,"Pass") -> 0 | D20: =COUNTIFS('UAT Test Cases'!$B$2:$B$117,$A20,'UAT Test Cases'!$J$2:$J$117,"Fail") -> 0 | E20: =COUNTIFS('UAT Test Cases'!$B$2:$B$117,$A20,'UAT Test Cases'!$J$2:$J$117,"Blocked") -> 0 | F20: =COUNTIFS('UAT Test Cases'!$B$2:$B$117,$A20,'UAT Test Cases'!$J$2:$J$117,"Not Tested") -> 4 | G20: =IFERROR((C20+D20+E20)/B20,0) -> 0
A21: Investment / Gold | B21: =COUNTIF('UAT Test Cases'!$B$2:$B$117,$A21) -> 5 | C21: =COUNTIFS('UAT Test Cases'!$B$2:$B$117,$A21,'UAT Test Cases'!$J$2:$J$117,"Pass") -> 0 | D21: =COUNTIFS('UAT Test Cases'!$B$2:$B$117,$A21,'UAT Test Cases'!$J$2:$J$117,"Fail") -> 0 | E21: =COUNTIFS('UAT Test Cases'!$B$2:$B$117,$A21,'UAT Test Cases'!$J$2:$J$117,"Blocked") -> 0 | F21: =COUNTIFS('UAT Test Cases'!$B$2:$B$117,$A21,'UAT Test Cases'!$J$2:$J$117,"Not Tested") -> 5 | G21: =IFERROR((C21+D21+E21)/B21,0) -> 0
A22: Budgeting | B22: =COUNTIF('UAT Test Cases'!$B$2:$B$117,$A22) -> 5 | C22: =COUNTIFS('UAT Test Cases'!$B$2:$B$117,$A22,'UAT Test Cases'!$J$2:$J$117,"Pass") -> 0 | D22: =COUNTIFS('UAT Test Cases'!$B$2:$B$117,$A22,'UAT Test Cases'!$J$2:$J$117,"Fail") -> 0 | E22: =COUNTIFS('UAT Test Cases'!$B$2:$B$117,$A22,'UAT Test Cases'!$J$2:$J$117,"Blocked") -> 0 | F22: =COUNTIFS('UAT Test Cases'!$B$2:$B$117,$A22,'UAT Test Cases'!$J$2:$J$117,"Not Tested") -> 5 | G22: =IFERROR((C22+D22+E22)/B22,0) -> 0
... A33: Desktop Companion | B33: =COUNTIF('UAT Test Cases'!$B$2:$B$117,$A33) -> 2 | C33: =COUNTIFS('UAT Test Cases'!$B$2:$B$117,$A33,'UAT Test Cases'!$J$2:$J$117,"Pass") -> 0 | D33: =COUNTIFS('UAT Test Cases'!$B$2:$B$117,$A33,'UAT Test Cases'!$J$2:$J$117,"Fail") -> 0 | E33: =COUNTIFS('UAT Test Cases'!$B$2:$B$117,$A33,'UAT Test Cases'!$J$2:$J$117,"Blocked") -> 0 | F33: =COUNTIFS('UAT Test Cases'!$B$2:$B$117,$A33,'UAT Test Cases'!$J$2:$J$117,"Not Tested") -> 2 | G33: =IFERROR((C33+D33+E33)/B33,0) -> 0

Sheet UAT Test Cases
A1: Test ID | B1: Module | C1: Feature | D1: Scenario | E1: Preconditions | F1: Test Steps | G1: Expected Result | H1: Priority | I1: Phase | J1: Status | K1: Actual Result / Notes | L1: Tested By | M1: Date Tested
A2: ONB-01 | B2: Onboarding | C2: First-run experience | D2: Welcome & philosophy explainer displays | E2: Fresh install, first launch | F2: Install app and open for the first time | G2: Welcome screens explain the minimal-interaction philosophy in plain language before any setup is requested | H2: Medium | I2: Milestone C | J2: Not Tested
A3: ONB-02 | B3: Onboarding | C3: Permission rationale | D3: Notification access request shows rationale first | E3: Onboarding in progress | F3: Reach the notification-access step | G3: A one-sentence explanation appears before the system permission dialog, not after | H3: Critical | I3: Milestone C | J3: Not Tested
A4: ONB-03 | B4: Onboarding | C4: Permission decline handling | D4: Declining notification access is handled gracefully | E4: On the permission step | F4: Deny the notification access request | G4: App does not crash; a clear path to grant access later from Settings is shown, no dead end | H4: Critical | I4: Milestone C | J4: Not Tested
A5: ONB-04 | B5: Onboarding | C5: Completion state | D5: Onboarding ends on the correct Home empty state | E5: Onboarding just completed, zero data | F5: Complete all onboarding steps | G5: Home screen shows the zero-transaction empty state, not an error or blank screen | H5: Medium | I5: Milestone C | J5: Not Tested
A6: NOT-01 | B6: Notification Capture | C6: Bank capture — CIMB | D6: CIMB Clicks notification is captured | E6: Notification access granted, CIMB Clicks installed | F6: Trigger a real CIMB transaction notification | G6: Notification is captured into the raw staging buffer within a few seconds | H6: Critical | I6: A2 | J6: Not Tested
A7: NOT-02 | B7: Notification Capture | C7: Bank capture — Maybank | D7: Maybank2u notification is captured | E7: Notification access granted, Maybank2u installed | F7: Trigger a real Maybank2u transaction notification | G7: Notification is captured into the raw staging buffer | H7: Critical | I7: A2 | J7: Not Tested
A8: NOT-03 | B8: Notification Capture | C8: Bank capture — BSN | D8: BSN notification is captured | E8: Notification access granted, BSN app installed | F8: Trigger a real BSN transaction notification | G8: Notification is captured into the raw staging buffer | H8: Critical | I8: A2 | J8: Not Tested
A9: NOT-04 | B9: Notification Capture | C9: Allowlist enforcement | D9: Non-allowlisted app notifications are ignored | E9: Any non-finance app installed (e.g. a messaging app) | F9: Receive a notification from a non-allowlisted app | G9: Notification is not captured, stored, or processed in any way | H9: Critical | I9: A2 | J9: Not Tested
A10: NOT-05 | B10: Notification Capture | C10: Background reliability | D10: Capture works while app is backgrounded or killed | E10: App backgrounded or force-closed | F10: Trigger a bank notification while the app isn't in the foreground | G10: Notification is still captured and later reflected in the transaction list once opened | H10: Critical | I10: A2 | J10: Not Tested
A11: NOT-06 | B11: Notification Capture | C11: Proactive app detection | D11: New finance app install triggers a suggestion | E11: A new bank/e-wallet app is installed on the device | F11: Install e.g. Boost after Sciuro is already set up | G11: A one-tap suggestion appears offering to track the newly installed app | H11: Low | I11: B (automation) | J11: Not Tested
A12: PAR-01 | B12: Parsing | C12: CIMB — DuitNow QR | D12: CIMB DuitNow QR payment parses correctly | E12: A real CIMB DuitNow QR notification exists | F12: Let the notification be parsed | G12: Amount, merchant, and channel (DuitNow QR) are all correctly extracted | H12: Critical | I12: A3 | J12: Not Tested
A13: PAR-02 | B13: Parsing | C13: Maybank — FPX | D13: Maybank FPX payment parses correctly | E13: A real Maybank FPX notification exists | F13: Let the notification be parsed | G13: Amount, merchant, and channel (FPX) are correctly extracted | H13: Critical | I13: A3 | J13: Not Tested
... A117: DSK-02 | B117: Desktop Companion | C117: Lottie fallback on desktop | D117: Desktop correctly falls back where Lottie doesn't render | E117: A moment that uses Lottie on Android (e.g. empty state) | F117: View the equivalent screen on desktop | G117: A static image appears in place of the animation, no error or blank space | H117: Low | I117: Deferred/Future | J117: Not Tested
